setup.py
Spray.egg-info/PKG-INFO
Spray.egg-info/SOURCES.txt
Spray.egg-info/dependency_links.txt
Spray.egg-info/entry_points.txt
Spray.egg-info/not-zip-safe
Spray.egg-info/requires.txt
Spray.egg-info/top_level.txt
spray/__init__.py
spray/spray.py